CHANGELOG.md
LICENSE
MANIFEST.in
README.md
setup.cfg
setup.py
src/mkdocs_interwiki/__init__.py
src/mkdocs_interwiki/interwiki.py
src/mkdocs_interwiki/plugin.py
src/mkdocs_interwiki.egg-info/PKG-INFO
src/mkdocs_interwiki.egg-info/SOURCES.txt
src/mkdocs_interwiki.egg-info/dependency_links.txt
src/mkdocs_interwiki.egg-info/entry_points.txt
src/mkdocs_interwiki.egg-info/not-zip-safe
src/mkdocs_interwiki.egg-info/requires.txt
src/mkdocs_interwiki.egg-info/top_level.txt