Metadata-Version: 2.1
Name: mkdocs-interwiki
Version: 0.1.3
Summary: DokuWiki-like InterWiki links for MkDocs
Home-page: https://github.com/yourname/mkdocs-interwiki
Author: Gobidesert
Author-email: gobidesert.mf@gmail.com
License: MIT
Project-URL: Source, https://github.com/yourname/mkdocs-interwiki
Project-URL: Tracker, https://github.com/yourname/mkdocs-interwiki/issues
Keywords: mkdocs,markdown,interwiki,dokuwiki,plugin
Platform: UNKNOWN
Classifier: Development Status :: 3 - Alpha
Classifier: Framework :: MkDocs
Classifier: Intended Audience :: Developers
Classifier: License :: OSI Approved :: MIT License
Classifier: Programming Language :: Python
Classifier: Programming Language :: Python :: 3
Classifier: Programming Language :: Python :: 3 :: Only
Classifier: Programming Language :: Python :: 3.8
Classifier: Programming Language :: Python :: 3.9
Classifier: Programming Language :: Python :: 3.10
Classifier: Programming Language :: Python :: 3.11
Classifier: Programming Language :: Python :: 3.12
Classifier: Topic :: Documentation
Classifier: Topic :: Text Processing :: Markup
Requires-Python: >=3.8
License-File: LICENSE
